BioLector/__init__.py
BioLector/biolector.py
BioLector/calculate.py
BioLectorPy-0.2.0.dist-info/LICENSE
BioLectorPy-0.2.0.dist-info/METADATA
BioLectorPy-0.2.0.dist-info/WHEEL
BioLectorPy-0.2.0.dist-info/top_level.txt
BioLectorPy-0.2.0.dist-info/RECORD
